polotsk/__init__.py
polotsk/external.py
polotsk/internal.py
polotsk/main.py
polotsk_admin/__init__.py
polotsk_admin/__main__.py
polotsk_admin/main.py
polotsk_admin/app/main/__init__.py
polotsk_admin/app/main/main.py
polotsk_pro-1.1.1.dist-info/LICENSE
polotsk_pro-1.1.1.dist-info/METADATA
polotsk_pro-1.1.1.dist-info/WHEEL
polotsk_pro-1.1.1.dist-info/top_level.txt
polotsk_pro-1.1.1.dist-info/RECORD
