Metadata-Version: 2.1
Name: polotsk_pro
Version: 1.1.1
Summary: This is polotsk module
Keywords: polotsk python
Classifier: Programming Language :: Python :: 3.11
Classifier: License :: OSI Approved :: MIT License
Classifier: Operating System :: OS Independent
Requires-Python: >=3.11
License-File: LICENSE
